conserver/__init__.py
conserver/cli.py
conserver/commands/__init__.py
conserver/commands/config.py
conserver/commands/images.py
conserver/commands/logs.py
conserver/commands/restart.py
conserver/commands/start.py
conserver/commands/status.py
conserver/commands/stop.py
conserver/commands/upgrade.py
conserver/config_manager.py
conserver/console.py
conserver/docker_ops.py
conserver/exceptions.py
conserver/health.py
conserver/image_registry.py
conserver_cli-0.2.0.dist-info/LICENSE
conserver_cli-0.2.0.dist-info/METADATA
conserver_cli-0.2.0.dist-info/WHEEL
conserver_cli-0.2.0.dist-info/entry_points.txt
conserver_cli-0.2.0.dist-info/RECORD
