Metadata-Version: 2.1
Name: conserver-cli
Version: 0.2.0
Summary: CLI tool to manage vcon-server Docker containers
Home-page: https://github.com/vcon-dev/vcon-server-cli
License: MIT
Keywords: vcon,docker,cli,conserver,voice-conversation
Author: Thomas Howe
Author-email: thomas@strolid.com
Requires-Python: >=3.10,<4.0
Classifier: Development Status :: 4 - Beta
Classifier: Environment :: Console
Classifier: Intended Audience :: Developers
Classifier: License :: OSI Approved :: MIT License
Classifier: Operating System :: OS Independent
Classifier: Programming Language :: Python :: 3
Classifier: Programming Language :: Python :: 3.10
Classifier: Programming Language :: Python :: 3.11
Classifier: Programming Language :: Python :: 3.12
Classifier: Topic :: Software Development :: Build Tools
Classifier: Topic :: System :: Systems Administration
Requires-Dist: click (>=8.1.7,<8.2.0)
Requires-Dist: docker (>=7.1.0,<8.0.0)
Requires-Dist: httpx (>=0.27.0,<0.28.0)
Requires-Dist: pydantic (>=2.6.0,<3.0.0)
Requires-Dist: pydantic-settings (>=2.2.0,<3.0.0)
Requires-Dist: python-dotenv (>=1.0.1,<2.0.0)
Requires-Dist: pyyaml (>=6.0.2,<7.0.0)
Requires-Dist: rich (>=13.7.0,<14.0.0)
Requires-Dist: typer[all] (>=0.12.0,<0.13.0)
Project-URL: Repository, https://github.com/vcon-dev/vcon-server-cli
